main.py
ravro-0.0.0.dist-info/METADATA
ravro-0.0.0.dist-info/WHEEL
ravro-0.0.0.dist-info/top_level.txt
ravro-0.0.0.dist-info/RECORD
