Metadata-Version: 2.4
Name: ravro
Version: 0.0.0
Summary: Coming soon
Author-email: Billy Doyle <50842911+billy-doyle@users.noreply.github.com>
Requires-Python: >=3.11
